banksy/__init__.py
banksy/cluster_methods.py
banksy/csr_operations.py
banksy/embed_banksy.py
banksy/initialize_banksy.py
banksy/labels.py
banksy/main.py
banksy/plot_banksy.py
banksy/run_banksy.py
banksy_utils/__init__.py
banksy_utils/cluster_utils.py
banksy_utils/color_lists.py
banksy_utils/filter_utils.py
banksy_utils/load_data.py
banksy_utils/pca.py
banksy_utils/plot_utils.py
banksy_utils/plotting.py
banksy_utils/preprocessing.py
banksy_utils/refine_clusters.py
banksy_utils/slideseq_ref_data.py
banksy_utils/time_utils.py
banksy_utils/umap_pca.py
banksy_py-0.0.7.dist-info/LICENSE.md
banksy_py-0.0.7.dist-info/METADATA
banksy_py-0.0.7.dist-info/WHEEL
banksy_py-0.0.7.dist-info/top_level.txt
banksy_py-0.0.7.dist-info/RECORD
